{
  "hash": "8885e0d8",
  "browserHash": "f5506ae5",
  "optimized": {
    "vue": {
      "src": "../../../../node_modules/.pnpm/vue@3.2.47/node_modules/vue/dist/vue.runtime.esm-bundler.js",
      "file": "vue.js",
      "fileHash": "0e9f3d71",
      "needsInterop": false
    },
    "three": {
      "src": "../../../../node_modules/.pnpm/three@0.150.1/node_modules/three/build/three.module.js",
      "file": "three.js",
      "fileHash": "83b7f56c",
      "needsInterop": false
    },
    "@tresjs/cientos": {
      "src": "../../../../node_modules/.pnpm/@tresjs+cientos@2.0.0-alpha.5_three@0.150.1/node_modules/@tresjs/cientos/dist/trescientos.js",
      "file": "@tresjs_cientos.js",
      "fileHash": "8aa5eace",
      "needsInterop": false
    },
    "@stackblitz/sdk": {
      "src": "../../../../node_modules/.pnpm/@stackblitz+sdk@1.8.2/node_modules/@stackblitz/sdk/bundles/sdk.m.js",
      "file": "@stackblitz_sdk.js",
      "fileHash": "a975a8b1",
      "needsInterop": false
    },
    "gsap": {
      "src": "../../../../node_modules/.pnpm/gsap@3.11.5/node_modules/gsap/index.js",
      "file": "gsap.js",
      "fileHash": "4e5151fd",
      "needsInterop": false
    },
    "@vueuse/core": {
      "src": "../../../../node_modules/.pnpm/@vueuse+core@9.13.0/node_modules/@vueuse/core/index.mjs",
      "file": "@vueuse_core.js",
      "fileHash": "62e3edb1",
      "needsInterop": false
    },
    "@alvarosabu/utils": {
      "src": "../../../../node_modules/.pnpm/@alvarosabu+utils@2.3.0/node_modules/@alvarosabu/utils/dist/as-utils.js",
      "file": "@alvarosabu_utils.js",
      "fileHash": "07b617fe",
      "needsInterop": false
    }
  },
  "chunks": {
    "chunk-4QXXOI63": {
      "file": "chunk-4QXXOI63.js"
    },
    "chunk-LZPJ5JBW": {
      "file": "chunk-LZPJ5JBW.js"
    },
    "chunk-JC4IRQUL": {
      "file": "chunk-JC4IRQUL.js"
    }
  }
}